kirami/__init__.py
kirami/config/__init__.py
kirami/config/config.py
kirami/config/path.py
kirami/config/utils.py
kirami/database/__init__.py
kirami/database/models/argot.py
kirami/database/models/group.py
kirami/database/models/user.py
kirami/depends.py
kirami/event.py
kirami/exception.py
kirami/hook.py
kirami/log.py
kirami/matcher.py
kirami/matcher.pyi
kirami/message.py
kirami/message.pyi
kirami/patch.py
kirami/permission.py
kirami/py.typed
kirami/rule.py
kirami/server/__init__.py
kirami/server/api.py
kirami/server/server.py
kirami/service/__init__.py
kirami/service/access.py
kirami/service/controller.py
kirami/service/limiter.py
kirami/service/manager.py
kirami/service/service.py
kirami/service/subject.py
kirami/state.py
kirami/typing.py
kirami/utils/__init__.py
kirami/utils/downloader.py
kirami/utils/helpers.py
kirami/utils/jsondata.py
kirami/utils/memcache.py
kirami/utils/renderer/__init__.py
kirami/utils/renderer/template/github-markdown.css
kirami/utils/renderer/template/highlight-dark.css
kirami/utils/renderer/template/highlight-light.css
kirami/utils/renderer/template/markdown.html
kirami/utils/request/__init__.py
kirami/utils/request/fake_user_agent.json
kirami/utils/request/utils.py
kirami/utils/resource.py
kirami/utils/scheduler.py
kirami/utils/utils.py
kirami/utils/webview.py
kirami/utils/webwright.py
kirami/version.py
kiramibot-0.3.5.dist-info/METADATA
kiramibot-0.3.5.dist-info/WHEEL
kiramibot-0.3.5.dist-info/licenses/LICENSE
kiramibot-0.3.5.dist-info/RECORD
